zwack/__init__.py
zwack/__main__.py
zwack/ascii.py
zwack/praise.py
zwack-2.2.0.dist-info/LICENSE
zwack-2.2.0.dist-info/METADATA
zwack-2.2.0.dist-info/WHEEL
zwack-2.2.0.dist-info/top_level.txt
zwack-2.2.0.dist-info/RECORD
