Metadata-Version: 2.1
Name: zwack
Version: 2.2.0
Summary: zwackkk
Home-page: UNKNOWN
Author: codemonkey51
Author-email: pypi@codemonkey51.dev
License: UNKNOWN
Platform: UNKNOWN
Classifier: Programming Language :: Python :: 3
Classifier: License :: OSI Approved :: MIT License
Classifier: Operating System :: OS Independent
Requires-Python: >=3.6
